feng_server_time/__init__.py
feng_server_time/__main__.py
feng_server_time/server.py
feng_server_time-0.1.0.dist-info/METADATA
feng_server_time-0.1.0.dist-info/WHEEL
feng_server_time-0.1.0.dist-info/entry_points.txt
feng_server_time-0.1.0.dist-info/RECORD
